[{"pk":1,"model":"products.producer","fields":{"name":"starnutrition","friendly_name":"Star Nutrition"}},{"pk":2,"model":"products.producer","fields":{"name":"optimumnitrition","friendly_name":"Optimum Nutrition"}},{"pk":3,"model":"products.producer","fields":{"name":"barebells","friendly_name":"Barebells"}},{"pk":4,"model":"products.producer","fields":{"name":"goodlife","friendly_name":"Goodlife"}},{"pk":5,"model":"products.producer","fields":{"name":"mutant","friendly_name":"Mutant"}},{"pk":6,"model":"products.producer","fields":{"name":"chainednutrition","friendly_name":"Chained Nutrition"}},{"pk":7,"model":"products.producer","fields":{"name":"swedishsupplements","friendly_name":"Swedish Supplements"}},{"pk":8,"model":"products.producer","fields":{"name":"smartsupps","friendly_name":"Smart Supps"}},{"pk":9,"model":"products.producer","fields":{"name":"myfitness","friendly_name":"MyFitness"}}]